mcp_data_analzyer/__init__.py
mcp_data_analzyer/__main__.py
mcp_data_analzyer/core.py
mcp_data_analzyer/main.py
mcp_data_analzyer-0.1.11.dist-info/METADATA
mcp_data_analzyer-0.1.11.dist-info/WHEEL
mcp_data_analzyer-0.1.11.dist-info/entry_points.txt
mcp_data_analzyer-0.1.11.dist-info/top_level.txt
mcp_data_analzyer-0.1.11.dist-info/RECORD
